example.py
pyaze/__init__.py
pyaze-1.3.dist-info/LICENSE.txt
pyaze-1.3.dist-info/METADATA
pyaze-1.3.dist-info/WHEEL
pyaze-1.3.dist-info/top_level.txt
pyaze-1.3.dist-info/RECORD
