Metadata-Version: 2.1
Name: pyaze
Version: 1.3
Summary: Python Azərbaycan dilində daha çox məlumat üçün kömək() funksiyasını daxil edin.
Home-page: https://teymuur.github.io
Author: Teymur
Author-email: teymur_babayev08@yahoo.com
Classifier: Programming Language :: Python :: 3
Classifier: License :: OSI Approved :: MIT License
Classifier: Operating System :: OS Independent
Requires-Python: >=3.0
License-File: LICENSE.txt
